omie/__init__.py
omie/omie.py
omie-0.0.0.dist-info/METADATA
omie-0.0.0.dist-info/WHEEL
omie-0.0.0.dist-info/entry_points.txt
omie-0.0.0.dist-info/top_level.txt
omie-0.0.0.dist-info/RECORD
