Metadata-Version: 2.1
Name: omie
Version: 0.0.0
Summary: Libreria de interacción con OMIE
Home-page: http://www.gisce.net
Author: Adrià Orellana
Author-email: aorellana@gisce.net
License: General Public Licence 2
Platform: UNKNOWN
Provides: omie
Requires-Dist: zeep
